MANIFEST.in
README.md
VERSION.txt
setup.py
fi/__init__.py
fi.egg-info/PKG-INFO
fi.egg-info/SOURCES.txt
fi.egg-info/dependency_links.txt
fi.egg-info/not-zip-safe
fi.egg-info/top_level.txt