Metadata-Version: 1.2
Name: fi
Version: 0.0.2
Summary: The file open library the government doesn't want you to know about
Home-page: https://github.com/python-efficiency/fi
Author: python-efficiency
Author-email: fi.pythonefficiency@gmail.com
License: MIT
Platform: UNKNOWN
Requires-Python: >=3.5
